gyerpsdkcore/__init__.py
gyerpsdkcore/api/__init__.py
gyerpsdkcore/api/base.py
gyerpsdkcore/api/item.py
gyerpsdkcore/api/trade.py
gyerpsdkcore/client/__init__.py
gyerpsdkcore/client/base.py
gy_erp_sdk_core-0.0.3.dist-info/LICENSE
gy_erp_sdk_core-0.0.3.dist-info/METADATA
gy_erp_sdk_core-0.0.3.dist-info/WHEEL
gy_erp_sdk_core-0.0.3.dist-info/top_level.txt
gy_erp_sdk_core-0.0.3.dist-info/RECORD
