Metadata-Version: 2.1
Name: gy-erp-sdk-core
Version: 0.0.3
Summary: gy erp api Python sdk.
Home-page: https://github.com/stevenQiang
Author: Steven
Author-email: qianggao7@gmail.com
License: cc
Keywords: 管易云,sdk,erp
Platform: any
Requires-Python: >=3
